ICP-2.1.1.html
MANIFEST.in
Makefile
README
setup.py
Examples/README
Examples/SydneyOpera.jpg
Examples/SydneyOpera2.jpg
Examples/binary_image_registration_example1.py
Examples/binary_image_registration_example2.py
Examples/cleanup_directory.py
Examples/color_image_registration_with_corner_pixels_example1.py
Examples/color_image_registration_with_edge_pixels_example1.py
Examples/color_image_registration_with_edge_pixels_example2.py
Examples/color_image_registration_with_edge_pixels_example3.py
Examples/gen_synthetic__model_and_data.py
Examples/highway.jpg
Examples/highway2.jpg
Examples/newline1.jpg
Examples/newline2.jpg
Examples/square.jpg
Examples/square2.jpg
Examples/textured.jpg
Examples/textured2.jpg
Examples/triangle1.jpg
Examples/triangle2.jpg
ExamplesICPImageScanner/ICPforOneSubimagePair.py
ExamplesICPImageScanner/ICPforScannerDump_no_intermediate_results.py
ExamplesICPImageScanner/ICPforScannerDump_show_intermediate_results.py
ExamplesICPImageScanner/README
ExamplesICPImageScanner/RunICPImageScanner.py
ExamplesICPImageScanner/cleanup_scanner_directory.py
ExamplesICPImageScanner/tommy_chang1.jpg
ExamplesICPImageScanner/tommy_chang2.jpg
ICP/ICP.py
ICP/__init__.py
ICP.egg-info/PKG-INFO
ICP.egg-info/SOURCES.txt
ICP.egg-info/dependency_links.txt
ICP.egg-info/top_level.txt
ICPImageScanner/ICPImageScanner.py
ICPImageScanner/__init__.py
TestICP/ICP.py
TestICP/Test.py
TestICP/TestFontFileAvailability.py
TestICP/TestPixelAcquisitionData.py
TestICP/TestPixelAcquisitionModel.py
TestICP/linedata.jpg
TestICP/linemodel.jpg