Metadata-Version: 1.1
Name: ICP
Version: 2.1.1
Summary: A Python module for registering a photo with a database image of the same scene
Home-page: https://engineering.purdue.edu/kak/distICP/ICP-2.1.1.html
Author: Avinash Kak
Author-email: kak@purdue.edu
License: Python Software Foundation License
Download-URL: https://engineering.purdue.edu/kak/distICP/ICP-2.1.1.tar.gz
Keywords: image processing,image registration,computer vision
Platform: All platforms
Classifier: Topic :: Scientific/Engineering :: Image Recognition
Classifier: Programming Language :: Python :: 2.7
Classifier: Programming Language :: Python :: 3.5
